TherapeuticNLP/__init__.py
TherapeuticNLP/input_data/.gitkeep
TherapeuticNLP/input_data/__init__.py
TherapeuticNLP/input_data/high_001.txt
TherapeuticNLP/input_data/high_011.txt
TherapeuticNLP/input_data/low_020.txt
TherapeuticNLP/output_data/__init__.py
TherapeuticNLP/scripts/__init__.py
TherapeuticNLP/scripts/conversation_analysis_processor.py
TherapeuticNLP/scripts/run_extraction.py
TherapeuticNLP/scripts/transcript_metrics.py
therapeuticnlp-1.0.0.dist-info/LICENSE
therapeuticnlp-1.0.0.dist-info/METADATA
therapeuticnlp-1.0.0.dist-info/WHEEL
therapeuticnlp-1.0.0.dist-info/entry_points.txt
therapeuticnlp-1.0.0.dist-info/top_level.txt
therapeuticnlp-1.0.0.dist-info/RECORD
