Metadata-Version: 2.2
Name: TherapeuticNLP
Version: 1.0.0
Summary: A multi-dimensional Natural Language Processing (NLP) framework for analyzing and assessing the quality of therapeutic conversations
Home-page: https://github.com/R-Niloy/Estimating-Quality-in-Therapeutic-Conversations-A-Multi-Dimensional-NLP-Framework
Author: Roy Niloy, Sarmed Shaya, Dylan Weston and Zachary Cote
Author-email: "Roy Niloy, Sarmed Shaya, Dylan Weston and Zachary Cote" <its.royniloy@gmail.com>
License: MIT
Project-URL: Homepage, https://github.com/R-Niloy/Estimating-Quality-in-Therapeutic-Conversations-A-Multi-Dimensional-NLP-Framework
Project-URL: Bug Tracker, https://github.com/R-Niloy/Estimating-Quality-in-Therapeutic-Conversations-A-Multi-Dimensional-NLP-Framework/issues
Classifier: Programming Language :: Python :: 3
Classifier: License :: OSI Approved :: MIT License
Classifier: Operating System :: OS Independent
Classifier: Intended Audience :: Science/Research
Classifier: Topic :: Scientific/Engineering :: Artificial Intelligence
Requires-Python: >=3.6
License-File: LICENSE
Requires-Dist: pandas
Requires-Dist: nltk
Requires-Dist: transformers
Requires-Dist: promcse
Requires-Dist: sentence_transformers
Requires-Dist: scipy
Requires-Dist: statistics
Requires-Dist: openpyxl
Requires-Dist: scikit-learn
Requires-Dist: numpy
Provides-Extra: dev
Requires-Dist: pytest; extra == "dev"
Requires-Dist: pytest-cov; extra == "dev"
Requires-Dist: black; extra == "dev"
Requires-Dist: isort; extra == "dev"
Requires-Dist: flake8; extra == "dev"
Dynamic: author
Dynamic: home-page
Dynamic: requires-python
